{
  "locations": [
    {
      "id": "dorm",
      "name": "宿舍",
      "description": "温馨的小窝，是休息和恢复能量的地方。每天从这里出发，开始新的一天。",
      "icon": "🏠",
      "position": { "lat": 31.8830, "lng": 117.2870 },
      "type": "living",
      "npcs": [],
      "tasks": ["daily_1"],
      "buff": { "name": "舒适休息", "description": "能量恢复+10%", "duration_hours": 8, "effects": { "energy": 10 } },
      "hidden_events": ["morning_energy", "roommate_chat"],
      "hidden_event_chance": 0.12,
      "unlock_requirements": { "min_level": 1 },
      "first_discover_text": "回到宿舍，感觉全身都放松了下来。室友们正在讨论今天的课程安排..."
    },
    {
      "id": "canteen",
      "name": "第一食堂",
      "description": "校园最热闹的地方之一，各种美食汇聚于此，是补充能量的好去处。",
      "icon": "🍜",
      "position": { "lat": 31.8835, "lng": 117.2880 },
      "type": "food",
      "npcs": ["naruto"],
      "tasks": ["daily_canteen_task"],
      "buff": { "name": "饱餐一顿", "description": "能量+20，心情+5", "duration_hours": 4, "effects": { "energy": 20, "mood": 5 } },
      "hidden_events": ["secret_dish", "canteen_event"],
      "hidden_event_chance": 0.15,
      "unlock_requirements": { "min_level": 1 },
      "first_discover_text": "食堂里人来人往，饭菜的香味扑鼻而来。你发现了隐藏窗口的位置！"
    },
    {
      "id": "library",
      "name": "图书馆",
      "description": "知识的殿堂，安静的学习圣地。在这里专注力大幅提升，适合深度学习。",
      "icon": "📚",
      "position": { "lat": 31.8840, "lng": 117.2865 },
      "type": "study",
      "npcs": ["naruto", "sasuke"],
      "tasks": ["main_library_task", "daily_word_task"],
      "buff": { "name": "知识光环", "description": "专注+25，学习效率+15%", "duration_hours": 3, "effects": { "focus": 25 } },
      "hidden_events": ["rare_book", "library_secret", "quiet_spot"],
      "hidden_event_chance": 0.18,
      "unlock_requirements": { "min_level": 1 },
      "first_discover_text": "推开图书馆的大门，安静的气息扑面而来。这里是阿游第一次觉醒的地方..."
    },
    {
      "id": "teaching_building",
      "name": "教学楼",
      "description": "日常上课的地方，有多媒体教室和自习室。穿梭于不同的教室，探索知识的海洋。",
      "icon": "🏫",
      "position": { "lat": 31.8838, "lng": 117.2875 },
      "type": "academic",
      "npcs": ["sasuke"],
      "tasks": ["main_class_task"],
      "buff": { "name": "学术氛围", "description": "压力+5，但任务经验+10%", "duration_hours": 4, "effects": { "stress": 5 } },
      "hidden_events": ["notice_board", "empty_classroom", "teacher_office"],
      "hidden_event_chance": 0.12,
      "unlock_requirements": { "min_level": 1 },
      "first_discover_text": "教学楼的公告栏前聚集了一些同学，似乎在讨论什么重要的事情..."
    },
    {
      "id": "sports_field",
      "name": "操场",
      "description": "宽阔的运动场，有跑道、篮球场和足球场。运动是释放压力、提升状态的好方式。",
      "icon": "🏃",
      "position": { "lat": 31.8825, "lng": 117.2868 },
      "type": "sports",
      "npcs": [],
      "tasks": ["daily_sports_task"],
      "buff": { "name": "运动达人", "description": "能量-10，压力-20，心情+15", "duration_hours": 6, "effects": { "energy": -10, "stress": -20, "mood": 15 } },
      "hidden_events": ["pickup_game", "sunrise_runner", "sports_fair"],
      "hidden_event_chance": 0.20,
      "unlock_requirements": { "min_level": 1 },
      "first_discover_text": "操场上正在进行一场激烈的篮球赛，你也忍不住加入了观众席..."
    },
    {
      "id": "garden",
      "name": "校园花园",
      "description": "宁静的绿色空间，有长椅和小池塘。是散步、冥想和放松心情的好地方。",
      "icon": "🌳",
      "position": { "lat": 31.8842, "lng": 117.2882 },
      "type": "leisure",
      "npcs": [],
      "tasks": ["side_relax_task"],
      "buff": { "name": "心灵治愈", "description": "心情+20，压力-15", "duration_hours": 5, "effects": { "mood": 20, "stress": -15 } },
      "hidden_events": ["cat_friend", "quiet_moment", "butterfly"],
      "hidden_event_chance": 0.25,
      "unlock_requirements": { "min_level": 2 },
      "first_discover_text": "花园里的花开得正艳，一阵微风吹过，带来淡淡的花香..."
    },
    {
      "id": "cafe",
      "name": "校园咖啡厅",
      "description": "提供咖啡和小点心的休闲空间，适合学习、小组讨论或一个人静静发呆。",
      "icon": "☕",
      "position": { "lat": 31.8833, "lng": 117.2878 },
      "type": "social",
      "npcs": ["naruto"],
      "tasks": ["side_cafe_task"],
      "buff": { "name": "咖啡加成", "description": "专注+15，但金币-5", "duration_hours": 3, "effects": { "focus": 15, "gold": -5 } },
      "hidden_events": ["study_group", "surprise_discount", "random_acquaintance"],
      "hidden_event_chance": 0.18,
      "unlock_requirements": { "min_level": 3 },
      "first_discover_text": "咖啡厅里弥漫着咖啡的香气，有几个学长正在激烈地讨论创业项目..."
    },
    {
      "id": "lab",
      "name": "实验楼",
      "description": "进行实验和科研的地方。充满神秘感，各种仪器设备琳琅满目。",
      "icon": "🔬",
      "position": { "lat": 31.8836, "lng": 117.2862 },
      "type": "academic",
      "npcs": ["sasuke"],
      "tasks": ["main_lab_task"],
      "buff": { "name": "科研探索", "description": "专注+20，获得额外经验+10%", "duration_hours": 4, "effects": { "focus": 20 } },
      "hidden_events": ["lab_discovery", "science_fair", "professor_encounter"],
      "hidden_event_chance": 0.15,
      "unlock_requirements": { "min_level": 2 },
      "first_discover_text": "实验楼里传来仪器运转的声音，你发现了一个尚未公开的研究项目..."
    },
    {
      "id": "bookstore",
      "name": "校园书店",
      "description": "各类书籍、文具和学习用品应有尽有。有时会有意想不到的折扣和惊喜。",
      "icon": "📖",
      "position": { "lat": 31.8844, "lng": 117.2872 },
      "type": "shop",
      "npcs": [],
      "tasks": ["side_bookstore_task"],
      "buff": { "name": "知识渴求", "description": "经验+15，但金币-10", "duration_hours": 2, "effects": { "gold": -10 } },
      "hidden_events": ["rare_book_discount", "author_meet", "book_recommendation"],
      "hidden_event_chance": 0.22,
      "unlock_requirements": { "min_level": 1 },
      "first_discover_text": "书架上摆满了各种书籍，你注意到角落里有一本被翻旧了的笔记本..."
    }
  ],
  "exploration_meta": {
    "total_locations": 9,
    "description": "校园探索地点数据库，每个地点都有独特的任务、NPC、buff和隐藏事件"
  }
}
